README.md
setup.cfg
setup.py
scrapesy/__init__.py
scrapesy.egg-info/PKG-INFO
scrapesy.egg-info/SOURCES.txt
scrapesy.egg-info/dependency_links.txt
scrapesy.egg-info/requires.txt
scrapesy.egg-info/top_level.txt