Metadata-Version: 2.1
Name: scrapesy
Version: 1.0.4
Summary: Simple Python web scraper/page fetcher with cache
Home-page: https://github.com/scoopgracie/scrapesy
Author: ScoopGracie
Author-email: scoopgracie@scoopgracie.com
License: MIT
Keywords: scrape,web,scraper,scraping
Platform: UNKNOWN
Classifier: Development Status :: 3 - Alpha
Classifier: Intended Audience :: Developers
Classifier: License :: OSI Approved :: MIT License
Classifier: Programming Language :: Python :: 3
Classifier: Programming Language :: Python :: 3.5
Classifier: Programming Language :: Python :: 3.6
Classifier: Programming Language :: Python :: 3.7
Classifier: Programming Language :: Python :: 3.8
Classifier: Programming Language :: Python :: 3.9
